MANIFEST.in
README
cook.el
setup.py
etc/_cook_complete
etc/bash-completion.sh
etc/cook
etc/elpa.el
etc/scripts.el
pycook/__init__.py
pycook/__main__.py
pycook/cook.py
pycook/elisp.py
pycook/insta.py
pycook/pty.py
pycook/test.py
pycook.egg-info/PKG-INFO
pycook.egg-info/SOURCES.txt
pycook.egg-info/dependency_links.txt
pycook.egg-info/entry_points.txt
pycook.egg-info/top_level.txt
pycook/recipes/__init__.py
pycook/recipes/apt.py
pycook/recipes/clojure.py
pycook/recipes/convert.py
pycook/recipes/docker.py
pycook/recipes/dpkg.py
pycook/recipes/emacs.py
pycook/recipes/examples.py
pycook/recipes/git.py
pycook/recipes/iphone.py
pycook/recipes/iso.py
pycook/recipes/java.py
pycook/recipes/linux.py
pycook/recipes/md.py
pycook/recipes/mount.py
pycook/recipes/net.py
pycook/recipes/org.py
pycook/recipes/package.py
pycook/recipes/passwd.py
pycook/recipes/pdf.py
pycook/recipes/pip.py
pycook/recipes/rust.py
pycook/recipes/self.py
pycook/recipes/ssl.py
pycook/recipes/str.py
pycook/recipes/txt.py